gradrack/__init__.py
gradrack/generators/__init__.py
gradrack/generators/adsr.py
gradrack/oscillators/__init__.py
gradrack/oscillators/oscillator_base.py
gradrack/oscillators/sinusoid.py
gradrack/synths/__init__.py
gradrack/synths/fm_synth.py
test/__init__.py
test/unit/__init__.py
test/unit/generators/__init__.py
test/unit/generators/test_adsr.py
test/unit/oscillators/__init__.py
test/unit/oscillators/test_oscillator.py
test/unit/oscillators/test_sinusoid.py
gradrack-0.0.3.dist-info/METADATA
gradrack-0.0.3.dist-info/WHEEL
gradrack-0.0.3.dist-info/top_level.txt
gradrack-0.0.3.dist-info/RECORD
