Metadata-Version: 2.1
Name: gradrack
Version: 0.0.3
Summary: A differentiable library of synthesiser components
Home-page: https://github.com/signas-qmul/gradrack
Author: SIGNAS
Author-email: b.j.hayes@se19.qmul.ac.uk
License: UNKNOWN
Platform: UNKNOWN
Classifier: Programming Language :: Python :: 3
Classifier: License :: OSI Approved :: MIT License
Classifier: Operating System :: OS Independent
Requires-Python: >=3.6
Requires-Dist: torch (==1.5.0)
